schzz/RealTime.py
schzz/Submit.py
schzz/__init__.py
schzz-0.25.dist-info/LICENSE
schzz-0.25.dist-info/METADATA
schzz-0.25.dist-info/WHEEL
schzz-0.25.dist-info/top_level.txt
schzz-0.25.dist-info/RECORD
