Metadata-Version: 2.1
Name: schzz
Version: 0.25
Summary: A way to make ml posts in my website
Home-page: https://github.com/Schwarzam
Author: Gustavo Schwarz
Author-email: gustavo.b.schwarz@gmail.com
License: UNKNOWN
Platform: UNKNOWN
Classifier: Programming Language :: Python :: 3
Classifier: License :: OSI Approved :: MIT License
Classifier: Operating System :: OS Independent
Requires-Dist: keras
Requires-Dist: numpy
Requires-Dist: requests
Requires-Dist: websocket-client
